cores/__init__.py
cores/const/__const.py
cores/const/__init__.py
cores/const/api/__init__.py
cores/const/api/api.py
cores/const/api/request.py
cores/const/common/__init__.py
cores/const/common/common_const.py
cores/const/common/environment_const.py
cores/const/common/msg_const.py
cores/const/common/path_const.py
cores/const/common/store_const.py
cores/const/common/string_const.py
cores/const/common/times_const.py
cores/const/common/types_const.py
cores/const/config/__init__.py
cores/const/config/data_const.py
cores/const/config/driver_const.py
cores/const/config/testlink_const.py
cores/const/mobile/__init__.py
cores/const/mobile/appium_const.py
cores/const/mobile/application_const.py
cores/const/mobile/command_const.py
cores/const/mobile/desired_capatibilities_const.py
cores/const/mobile/device_const.py
cores/const/mobile/interaction_const.py
cores/const/web/__init__.py
cores/const/web/browsers_const.py
cores/decorators/__init__.py
cores/decorators/handle_exception.py
cores/decorators/parse_config.py
cores/factory/__init__.py
cores/factory/request/__init__.py
cores/factory/request/base_factory.py
cores/factory/request/request_generator.py
cores/model/__init__.py
cores/model/db_conn.py
cores/model/environment.py
cores/model/request.py
cores/model/users.py
cores/utils/__init__.py
cores/utils/logger_util.py
cores/utils/backend/__init__.py
cores/utils/backend/data_setup_util.py
cores/utils/backend/database_util.py
cores/utils/backend/gitlab_util.py
cores/utils/backend/request_util.py
cores/utils/backend/swagger_parser_util.py
cores/utils/backend/verify_util.py
cores/utils/common/__init__.py
cores/utils/common/assertion_util.py
cores/utils/common/csv_util.py
cores/utils/common/execute_java_file.py
cores/utils/common/json_util.py
cores/utils/common/path_util.py
cores/utils/common/prepare_fake_data.py
cores/utils/common/prepare_object.py
cores/utils/common/store_util.py
cores/utils/common/string_util.py
cores/utils/common/time_util.py
Automation_Framework_by_Gauge-0.0.1.dist-info/LICENSE
Automation_Framework_by_Gauge-0.0.1.dist-info/METADATA
Automation_Framework_by_Gauge-0.0.1.dist-info/WHEEL
Automation_Framework_by_Gauge-0.0.1.dist-info/top_level.txt
Automation_Framework_by_Gauge-0.0.1.dist-info/RECORD
